AudioFeaturizer/__init__.py
AudioFeaturizer/_version.py
AudioFeaturizer/audio_featurizer.py
AudioFeaturizer-2.2.0.dist-info/LICENSE
AudioFeaturizer-2.2.0.dist-info/METADATA
AudioFeaturizer-2.2.0.dist-info/WHEEL
AudioFeaturizer-2.2.0.dist-info/top_level.txt
AudioFeaturizer-2.2.0.dist-info/RECORD
