Metadata-Version: 2.1
Name: AudioFeaturizer
Version: 2.2.0
Summary: Takes audio as input and returns computed features as a dataframe
Home-page: UNKNOWN
Author: Harish-Natarajan
Author-email: harishnatarajan24@gmail.com
License: MIT
Platform: UNKNOWN
Classifier: License :: OSI Approved :: MIT License
Classifier: Programming Language :: Python :: 3
Classifier: Programming Language :: Python :: 3.7
Requires-Python: >=3.7
Requires-Dist: librosa
Requires-Dist: pandas
Requires-Dist: numpy
Requires-Dist: matplotlib
